pychfs/__init__.py
pychfs/chfs.cpython-39-x86_64-linux-gnu.so
pychfs-0.0.1.dist-info/LICENSE
pychfs-0.0.1.dist-info/METADATA
pychfs-0.0.1.dist-info/WHEEL
pychfs-0.0.1.dist-info/entry_points.txt
pychfs-0.0.1.dist-info/top_level.txt
pychfs-0.0.1.dist-info/RECORD
