Metadata-Version: 2.1
Name: pychfs
Version: 0.0.1
Summary: CHFS Python bindings
Home-page: https://github.com/donkomura/PyCHFS
Author: Kazuki Obata, Sohei Koyama
Author-email: obata@hpcs.cs.tsukuba.ac.jp, skoyama@hpcs.cs.tsukuba.ac.jp
License-File: LICENSE
